nv2a_debug/__about__.py
nv2a_debug/__init__.py
nv2a_debug/_code_panel.py
nv2a_debug/_editor.py
nv2a_debug/_error_message.py
nv2a_debug/_file_menu.py
nv2a_debug/_input_panel.py
nv2a_debug/_input_sanitizer.py
nv2a_debug/_output_panel.py
nv2a_debug/_program_inputs_viewer.py
nv2a_debug/_program_outputs_viewer.py
nv2a_debug/_program_vertex_viewer.py
nv2a_debug/_register_view.py
nv2a_debug/_shader_program.py
nv2a_debug/_types.py
nv2a_debug/debugger.py
nv2a_debug/py_nv2a_vsh_emu.py
nv2a_debug/simulator.py
nv2a_debug-0.2.1.dist-info/METADATA
nv2a_debug-0.2.1.dist-info/WHEEL
nv2a_debug-0.2.1.dist-info/entry_points.txt
nv2a_debug-0.2.1.dist-info/licenses/LICENSE
nv2a_debug-0.2.1.dist-info/RECORD
