Metadata-Version: 2.4
Name: nv2a-debug
Version: 0.2.1
Summary: Simulator/debugger for the Xbox nv2a vertex shader
Project-URL: Documentation, https://github.com/abaire/nv2a_vsh_debug#readme
Project-URL: Issues, https://github.com/abaire/nv2a_vsh_debug/issues
Project-URL: Source, https://github.com/abaire/nv2a_vsh_debug
Author-email: Erik Abair <erik.abair@bearbrains.work>
License: This is free and unencumbered software released into the public domain.
License-File: LICENSE
Keywords: assembler,nv2a,nvidia,vertex shader,xbox
Classifier: Development Status :: 3 - Alpha
Classifier: Environment :: Console
Classifier: Intended Audience :: Developers
Classifier: Operating System :: OS Independent
Classifier: Programming Language :: Python
Classifier: Programming Language :: Python :: 3.11
Classifier: Programming Language :: Python :: 3.12
Classifier: Topic :: Software Development :: Debuggers
Requires-Python: >=3.11
Requires-Dist: cffi~=1.17.1
Requires-Dist: nv2a-vsh~=0.1.2
Requires-Dist: textual~=3.5.0
